printm
